palanystorage/__init__.py
palanystorage/const.py
palanystorage/exceptions.py
palanystorage/loader.py
palanystorage/log.py
palanystorage/schema.py
palanystorage/uri.py
palanystorage/cli/__init__.py
palanystorage/cli/main.py
palanystorage/dialects/__init__.py
palanystorage/dialects/alioss/__init__.py
palanystorage/dialects/alioss/pal_alioss.py
palanystorage/dialects/localfs/__init__.py
palanystorage/dialects/qiniu/__init__.py
palanystorage/dialects/qiniu/pal_qiniu.py
palanystorage/dialects/txcos/__init__.py
palanystorage/dialects/txcos/pal_txcos.py
palanystorage/engine/__init__.py
palanystorage/engine/base.py
palanystorage-0.1.8.dist-info/entry_points.txt
palanystorage-0.1.8.dist-info/licenses/LICENSE.txt
palanystorage-0.1.8.dist-info/WHEEL
palanystorage-0.1.8.dist-info/METADATA
palanystorage-0.1.8.dist-info/RECORD
